photobox/__init__.py
photobox/camera.py
photobox/common.py
photobox/debug.py
photobox/detections.py
photobox/photobox_app.py
photobox/stickyplate.py
photobox/utils.py
photobox/icons/calibrate.png
photobox/icons/camera.png
photobox/icons/crop.png
photobox/icons/detect.png
photobox/icons/model.png
photobox/icons/next.png
photobox/icons/next1.png
photobox/icons/predict.png
photobox/icons/prev.png
photobox/icons/process.png
photobox/icons/segment.png
photobox/icons/validate.png
photobox/tests/__init__.py
photobox/tests/test_photobox_app.py
photobox-0.0.3.dist-info/LICENSE
photobox-0.0.3.dist-info/METADATA
photobox-0.0.3.dist-info/WHEEL
photobox-0.0.3.dist-info/entry_points.txt
photobox-0.0.3.dist-info/top_level.txt
photobox-0.0.3.dist-info/RECORD
