Metadata-Version: 2.1
Name: photobox
Version: 0.0.3
Summary: A guizero application to image insect sticky plates
Home-page: https://github.com/kalfasyan/photobox
Author: Ioannis Kalfas
Author-email: kalfasyan@gmail.com
License: UNKNOWN
Keywords: photobox
Platform: UNKNOWN
Classifier: Programming Language :: Python :: 3.6
Classifier: Programming Language :: Python :: 3.7
Classifier: Programming Language :: Python :: 3.8
Classifier: Programming Language :: Python :: 3.9
Classifier: Programming Language :: Python :: 3.10
License-File: LICENSE
Requires-Dist: arrow (==1.2.2)
Requires-Dist: binaryornot (==0.4.4)
Requires-Dist: category-encoders (==2.4.0)
Requires-Dist: chardet (==4.0.0)
Requires-Dist: charset-normalizer (==2.0.12)
Requires-Dist: click (==8.1.3)
Requires-Dist: cookiecutter (==1.7.3)
Requires-Dist: guizero (==1.3.0)
Requires-Dist: idna (==3.3)
Requires-Dist: jinja2 (==3.1.2)
Requires-Dist: jinja2-time (==0.2.0)
Requires-Dist: joblib (==1.1.0)
Requires-Dist: lxml (==4.8.0)
Requires-Dist: markupsafe (==2.1.1)
Requires-Dist: matplotlib-inline (==0.1.3)
Requires-Dist: natsort (==8.1.0)
Requires-Dist: numpy (==1.22.3)
Requires-Dist: opencv-python (==4.5.5.64)
Requires-Dist: patsy (==0.5.2)
Requires-Dist: poyo (==0.5.0)
Requires-Dist: prompt-toolkit (==3.0.29)
Requires-Dist: pygments (==2.12.0)
Requires-Dist: python-slugify (==6.1.2)
Requires-Dist: requests (==2.27.1)
Requires-Dist: scikit-learn (==1.0.2)
Requires-Dist: statsmodels (==0.13.2)
Requires-Dist: text-unidecode (==1.3)
Requires-Dist: threadpoolctl (==3.1.0)
Requires-Dist: torch (==1.11.0)
Requires-Dist: torchaudio (==0.11.0)
Requires-Dist: torchvision (==0.12.0)
Requires-Dist: typing-extensions (==4.2.0)
Requires-Dist: urllib3 (==1.26.9)
Requires-Dist: seaborn
Requires-Dist: scipy
Requires-Dist: guizero
Requires-Dist: pandas (==1.4.2)
Requires-Dist: ipython (==8.2.0)
Requires-Dist: tqdm (==4.64.0)
Requires-Dist: six (==1.16.0)
